tmktpostgresql/postgresql.py
tmktpostgresql-1.0.0.dist-info/LICENSE
tmktpostgresql-1.0.0.dist-info/METADATA
tmktpostgresql-1.0.0.dist-info/WHEEL
tmktpostgresql-1.0.0.dist-info/RECORD
